asr_metrics/__init__.py
asr_metrics/cli.py
asr_metrics/diarization/__init__.py
asr_metrics/diarization/sm_diarization_metrics/__init__.py
asr_metrics/diarization/sm_diarization_metrics/cli.py
asr_metrics/diarization/sm_diarization_metrics/cookbook.py
asr_metrics/diarization/sm_diarization_metrics/utils.py
asr_metrics/diarization/sm_diarization_metrics/metrics/__init__.py
asr_metrics/diarization/sm_diarization_metrics/metrics/_version.py
asr_metrics/diarization/sm_diarization_metrics/metrics/base.py
asr_metrics/diarization/sm_diarization_metrics/metrics/binary_classification.py
asr_metrics/diarization/sm_diarization_metrics/metrics/detection.py
asr_metrics/diarization/sm_diarization_metrics/metrics/diarization.py
asr_metrics/diarization/sm_diarization_metrics/metrics/identification.py
asr_metrics/diarization/sm_diarization_metrics/metrics/matcher.py
asr_metrics/diarization/sm_diarization_metrics/metrics/segmentation.py
asr_metrics/diarization/sm_diarization_metrics/metrics/spotting.py
asr_metrics/diarization/sm_diarization_metrics/metrics/utils.py
asr_metrics/diarization/sm_diarization_metrics/metrics/words.py
asr_metrics/diarization/sm_diarization_metrics/metrics/errors/__init__.py
asr_metrics/diarization/sm_diarization_metrics/metrics/errors/identification.py
asr_metrics/diarization/sm_diarization_metrics/metrics/errors/segmentation.py
asr_metrics/diarization/sm_diarization_metrics/metrics/plot/__init__.py
asr_metrics/diarization/sm_diarization_metrics/metrics/plot/binary_classification.py
asr_metrics/wer/__init__.py
asr_metrics/wer/__main__.py
asr_metrics/wer/normalizers/__init__.py
asr_metrics/wer/normalizers/basic.py
asr_metrics/wer/normalizers/english.py
asr_metrics/wer/normalizers/english.yaml
speechmatics/__init__.py
speechmatics/adapters.py
speechmatics/batch_client.py
speechmatics/cli.py
speechmatics/cli_parser.py
speechmatics/client.py
speechmatics/config.py
speechmatics/constants.py
speechmatics/exceptions.py
speechmatics/helpers.py
speechmatics_python-4.0.9.dist-info/licenses/LICENSE.txt
speechmatics_python-4.0.9.dist-info/METADATA
speechmatics_python-4.0.9.dist-info/WHEEL
speechmatics_python-4.0.9.dist-info/entry_points.txt
speechmatics_python-4.0.9.dist-info/top_level.txt
speechmatics_python-4.0.9.dist-info/RECORD
