Metadata-Version: 2.4
Name: speechmatics-python
Version: 4.0.9
Summary: Python library and CLI for Speechmatics
Home-page: https://github.com/speechmatics/speechmatics-python/
Author: Speechmatics
Author-email: support@speechmatics.com
License: MIT
Project-URL: Documentation, https://speechmatics.github.io/speechmatics-python/
Project-URL: Source Code, https://github.com/speechmatics/speechmatics-python/
Classifier: Environment :: Console
Classifier: Intended Audience :: Developers
Classifier: Development Status :: 7 - Inactive
Classifier: License :: OSI Approved :: MIT License
Classifier: Operating System :: OS Independent
Classifier: Programming Language :: Python :: 3
Classifier: Programming Language :: Python :: 3.9
Classifier: Topic :: Multimedia :: Sound/Audio :: Speech
Classifier: Topic :: Software Development :: Libraries :: Python Modules
Requires-Python: >=3.9
License-File: LICENSE.txt
Requires-Dist: websockets>=10.0
Requires-Dist: httpx[http2]~=0.23
Requires-Dist: polling2~=0.5
Requires-Dist: toml~=0.10.2
Requires-Dist: tenacity~=8.2.3
Provides-Extra: metrics
Requires-Dist: docopt; extra == "metrics"
Requires-Dist: jiwer; extra == "metrics"
Requires-Dist: more-itertools; extra == "metrics"
Requires-Dist: pandas; extra == "metrics"
Requires-Dist: pyannote.core; extra == "metrics"
Requires-Dist: pyannote.database; extra == "metrics"
Requires-Dist: regex; extra == "metrics"
Requires-Dist: tabulate>=0.8.9; extra == "metrics"
Dynamic: author
Dynamic: author-email
Dynamic: classifier
Dynamic: description
Dynamic: description-content-type
Dynamic: home-page
Dynamic: license
Dynamic: license-file
Dynamic: project-url
Dynamic: provides-extra
Dynamic: requires-dist
Dynamic: requires-python
Dynamic: summary
